hermione/__init__.py
hermione/_version.py
hermione/cli/__init__.py
hermione/cli/main.py
hermione/cli/notebook.py
hermione/cli/project.py
hermione/cli/run.py
hermione/core/__init__.py
hermione/core/base.py
hermione/core/utils.py
hermione/core/analysis/__init__.py
hermione/core/analysis/_autoenconder.py
hermione/core/analysis/_cluster.py
hermione/core/analysis/_dimensionality_reduction.py
hermione/core/analysis/_feature_selection.py
hermione/core/analysis/_hypothesis_autopilot.py
hermione/core/analysis/_hypothesis_testing.py
hermione/core/analysis/_pca.py
hermione/core/analysis/_vif.py
hermione/core/model/__init__.py
hermione/core/model/_metrics.py
hermione/core/model/_trainer.py
hermione/core/model/_wrapper.py
hermione/core/preprocessing/__init__.py
hermione/core/preprocessing/_datadrift.py
hermione/core/preprocessing/_normalization.py
hermione/core/preprocessing/_preprocessing.py
hermione/core/preprocessing/_preprocessor.py
hermione/core/preprocessing/_text_vectorizer.py
hermione/core/visualization/__init__.py
hermione/core/visualization/_visualization.py
hermione/data/notebook_templates/barebones.ipynb
hermione/data/notebook_templates/catboost.ipynb
hermione/data/notebook_templates/mapping.json
hermione/data/notebook_templates/pycaret.ipynb
hermione/data/project_artifacts/barebones/api/__init__.py
hermione/data/project_artifacts/barebones/api/app.py
hermione/data/project_artifacts/barebones/api/myrequests.py
hermione/data/project_artifacts/barebones/notebooks/example_notebook.ipynb
hermione/data/project_artifacts/barebones/scripts/__init__.py
hermione/data/project_artifacts/barebones/scripts/predict.py
hermione/data/project_artifacts/barebones/scripts/train.py
hermione/data/project_artifacts/barebones/src/data_source/__init__.py
hermione/data/project_artifacts/barebones/src/data_source/spreadsheet.py
hermione/data/project_artifacts/sagemaker/README.md
hermione/data/project_artifacts/sagemaker/build_and_push.sh
hermione_ml-0.10.0.dist-info/LICENSE
hermione_ml-0.10.0.dist-info/METADATA
hermione_ml-0.10.0.dist-info/WHEEL
hermione_ml-0.10.0.dist-info/entry_points.txt
hermione_ml-0.10.0.dist-info/top_level.txt
hermione_ml-0.10.0.dist-info/RECORD
