Metadata-Version: 2.1
Name: hermione-ml
Version: 0.10.0
Summary: UNKNOWN
Home-page: https://github.com/A3Data/hermione
Author: A3Data
Author-email: hermione@a3data.com.br
License: Apache License 2.0
Keywords: machine learning mlops devops artificial intelligence
Platform: UNKNOWN
Classifier: Development Status :: 4 - Beta
Classifier: License :: OSI Approved :: Apache Software License
Classifier: Programming Language :: Python :: 3.8
Classifier: Programming Language :: Python :: 3.9
Classifier: Topic :: Scientific/Engineering :: Artificial Intelligence
Classifier: Topic :: Software Development
Requires-Python: >=3.8.0
License-File: LICENSE
Requires-Dist: Click
Requires-Dist: Jinja2
